pcDataLoader/__init__.py
pcdataloader-3.2.0.dist-info/METADATA
pcdataloader-3.2.0.dist-info/WHEEL
pcdataloader-3.2.0.dist-info/RECORD
